covid/__init__.py
covid/region.py
covid/types.py
covid/utils.py
covid/data/__init__.py
covid/data/cia_factbook.py
covid/data/data.py
covid/data/ibge.py
covid/data/ibge_demographic.py
covid/data/mortality.py
covid/datasets/brazil_healthcare_capacity.csv
covid/datasets/brazil_healthcare_capacity.xlsx
covid/datasets/cia_factbook-age_distribution.csv
covid/datasets/cia_factbook-age_distribution.xlsx
covid/datasets/cia_factbook-hospital_bed_density.csv
covid/datasets/cia_factbook-hospital_bed_density.md
covid/datasets/covid-mortality-imperial-college.csv
covid/datasets/contact_matrix/belgium-all.csv
covid/datasets/contact_matrix/belgium-physical.csv
covid/datasets/contact_matrix/finland-all.csv
covid/datasets/contact_matrix/finland-physical.csv
covid/datasets/contact_matrix/germany-all.csv
covid/datasets/contact_matrix/germany-physical.csv
covid/datasets/contact_matrix/great britain-all.csv
covid/datasets/contact_matrix/great britain-physical.csv
covid/datasets/contact_matrix/italy-all.csv
covid/datasets/contact_matrix/italy-physical.csv
covid/datasets/contact_matrix/luxembourg-all.csv
covid/datasets/contact_matrix/luxembourg-physical.csv
covid/datasets/contact_matrix/mean-all.csv
covid/datasets/contact_matrix/mean-physical.csv
covid/datasets/contact_matrix/netherlands-all.csv
covid/datasets/contact_matrix/netherlands-physical.csv
covid/datasets/contact_matrix/poland-all.csv
covid/datasets/contact_matrix/poland-physical.csv
covid/datasets/ibge_demographic/city-310620.csv
covid/datasets/ibge_demographic/city-330455.csv
covid/datasets/ibge_demographic/city-355030.csv
covid/datasets/ibge_demographic/city-530010.csv
covid/models/__init__.py
covid/models/model.py
covid/models/plot.py
covid/models/rseicha.py
covid/models/rseicha_demographic.py
covid/notebooks/demographics.ipynb
covid/notebooks/report.ipynb
covid/notebooks/.ipynb_checkpoints/demographics-checkpoint.ipynb
covid_models-0.1.0.dist-info/LICENSE
covid_models-0.1.0.dist-info/WHEEL
covid_models-0.1.0.dist-info/METADATA
covid_models-0.1.0.dist-info/RECORD
